kryptex/__init__.py
kryptex/__main__.py
kryptex/cli.py
kryptex_secure-1.0.0.dist-info/licenses/LICENSE
kryptex_secure-1.0.0.dist-info/METADATA
kryptex_secure-1.0.0.dist-info/WHEEL
kryptex_secure-1.0.0.dist-info/entry_points.txt
kryptex_secure-1.0.0.dist-info/top_level.txt
kryptex_secure-1.0.0.dist-info/RECORD
