Metadata-Version: 2.4
Name: kryptex-secure
Version: 1.0.0
Summary: Production-grade secure key wrapping and file encryption tool
Home-page: https://github.com/Sammy750-cyber/kryptex
Author: Adegboyega Samuel
Author-email: Your Name <your.email@example.com>
Maintainer-email: Your Name <your.email@example.com>
License: MIT
Project-URL: Homepage, https://github.com/Sammy750-cyber/kryptex
Project-URL: Documentation, https://github.com/Sammy750-cyber/kryptex/docs
Project-URL: Repository, https://github.com/Sammy750-cyber/kryptex
Project-URL: Bug Reports, https://github.com/Sammy750-cyber/kryptex/issues
Keywords: encryption,cryptography,security,aes-gcm,scrypt,key-management
Classifier: Development Status :: 4 - Beta
Classifier: Intended Audience :: Developers
Classifier: Intended Audience :: System Administrators
Classifier: Topic :: Security :: Cryptography
Classifier: License :: OSI Approved :: MIT License
Classifier: Programming Language :: Python :: 3
Classifier: Programming Language :: Python :: 3.8
Classifier: Programming Language :: Python :: 3.9
Classifier: Programming Language :: Python :: 3.10
Classifier: Programming Language :: Python :: 3.11
Classifier: Operating System :: OS Independent
Classifier: Environment :: Console
Requires-Python: >=3.8
License-File: LICENSE
Requires-Dist: cryptography>=41.0.0
Provides-Extra: dev
Requires-Dist: black>=22.0; extra == "dev"
Requires-Dist: flake8>=4.0; extra == "dev"
Requires-Dist: mypy>=0.950; extra == "dev"
Requires-Dist: pytest-cov>=3.0; extra == "dev"
Requires-Dist: pytest>=7.0; extra == "dev"
Dynamic: author
Dynamic: home-page
Dynamic: license-file
Dynamic: requires-python
